README.txt
setup.py
Products/__init__.py
Products.SimpleChat.egg-info/PKG-INFO
Products.SimpleChat.egg-info/SOURCES.txt
Products.SimpleChat.egg-info/dependency_links.txt
Products.SimpleChat.egg-info/entry_points.txt
Products.SimpleChat.egg-info/namespace_packages.txt
Products.SimpleChat.egg-info/not-zip-safe
Products.SimpleChat.egg-info/requires.txt
Products.SimpleChat.egg-info/top_level.txt
Products/SimpleChat/Makefile
Products/SimpleChat/SimpleChat.py
Products/SimpleChat/TODO.txt
Products/SimpleChat/__init__.py
Products/SimpleChat/changes.txt
Products/SimpleChat/readme.txt
Products/SimpleChat/scconfig.py
Products/SimpleChat/version.txt
Products/SimpleChat/i18n/SimpleChat-no.po
Products/SimpleChat/skins/simple_chat/jquery.min.js.dtml
Products/SimpleChat/skins/simple_chat/simple_chat_add.pt
Products/SimpleChat/skins/simple_chat/simple_chat_ban.pt
Products/SimpleChat/skins/simple_chat/simple_chat_banned.pt
Products/SimpleChat/skins/simple_chat/simple_chat_index.pt
Products/SimpleChat/skins/simple_chat/simple_chat_logs.pt
Products/SimpleChat/skins/simple_chat/simple_chat_report.pt
Products/SimpleChat/skins/simple_chat/simple_chat_report_submit.pt