Metadata-Version: 1.0
Name: Products.SimpleChat
Version: 1.0.4
Summary: A Zope (runs in pure Zope 2) product for chatting, simple and accessible.  Also support Ajax sending and retrieval of messages
Home-page: http://www.nidelven-it.no/d
Author: Morten W. Petersen
Author-email: info@nidelven-it.no
License: GPL
Keywords: python zope plone silva chat messaging acessibility ajax justrox
Platform: UNKNOWN
Classifier: Programming Language :: Python
Classifier: Framework :: Zope2
Classifier: License :: OSI Approved :: Zope Public License
Classifier: Operating System :: OS Independent
